backup_warden/__init__.py
backup_warden/app.py
backup_warden-1.0.15.dist-info/METADATA
backup_warden-1.0.15.dist-info/WHEEL
backup_warden-1.0.15.dist-info/entry_points.txt
backup_warden-1.0.15.dist-info/licenses/LICENSE
backup_warden-1.0.15.dist-info/RECORD
