Metadata-Version: 2.4
Name: backup_warden
Version: 1.0.15
Summary: Streamline your backup management with ease and simplicity
License-File: LICENSE
Author: Charles Thompson
Author-email: 01charles.t@gmail.com
Requires-Python: >=3.9,<4.0
Classifier: Programming Language :: Python :: 3
Classifier: Programming Language :: Python :: 3.9
Classifier: Programming Language :: Python :: 3.10
Classifier: Programming Language :: Python :: 3.11
Classifier: Programming Language :: Python :: 3.12
Classifier: Programming Language :: Python :: 3.13
Classifier: Programming Language :: Python :: 3.14
Requires-Dist: boto3 (>=1.41.5,<2.0.0)
Requires-Dist: configparser (>=7.2.0,<8.0.0)
Requires-Dist: fabric (>=3.2.2,<4.0.0)
Requires-Dist: loguru (>=0.7.3,<0.8.0)
Requires-Dist: packaging (>=25.0,<26.0)
Requires-Dist: paramiko (>=4.0.0,<5.0.0)
Requires-Dist: property (>=2.6.2,<3.0.0)
Requires-Dist: property-manager (>=3.0,<4.0)
Requires-Dist: requests (>=2.32.5,<3.0.0)
Requires-Dist: simpleeval (>=1.0.3,<2.0.0)
Requires-Dist: slack (>=0.0.2,<0.0.3)
Requires-Dist: slack-sdk (>=3.39.0,<4.0.0)
Requires-Dist: tabulate (>=0.9.0,<0.10.0)
